sync/__init__.py
sync/sync.py
sync_py-1.0.4.dist-info/LICENSE
sync_py-1.0.4.dist-info/METADATA
sync_py-1.0.4.dist-info/WHEEL
sync_py-1.0.4.dist-info/entry_points.txt
sync_py-1.0.4.dist-info/top_level.txt
sync_py-1.0.4.dist-info/RECORD
