Metadata-Version: 2.1
Name: sync-py
Version: 1.0.4
Summary: Consume Paybook Sync REST API without pain
Home-page: https://github.com/Paybook/sync-py
Author: Paybook
Author-email: aldo.escobar@paybook.com
License: MIT
Project-URL: Bug Reports, https://github.com/Paybook/sync-py/issues
Project-URL: Home, https://www.paybook.com/w/es/sync/site/home
Project-URL: Source, https://github.com/Paybook/sync-py
Keywords: paybook sync bank sat
Platform: UNKNOWN
Classifier: Development Status :: 3 - Alpha
Classifier: Intended Audience :: Developers
Classifier: Topic :: Software Development :: Build Tools
Classifier: License :: OSI Approved :: MIT License
Classifier: Programming Language :: Python :: 3
Classifier: Programming Language :: Python :: 3.5
Classifier: Programming Language :: Python :: 3.6
Classifier: Programming Language :: Python :: 3.7
Classifier: Programming Language :: Python :: 3.8
Requires-Python: !=3.0.*, !=3.1.*, !=3.2.*, !=3.3.*, !=3.4.*, <4
Requires-Dist: requests
Provides-Extra: dev
Provides-Extra: test
